{
  "name": "Isokaze",
  "constructionTime": "00:27:00",
  "constructionPools": [
    true,
    false,
    false,
    false,
    false
  ],
  "dropLocations": [
    [
      false,
      false,
      false,
      false,
      false,
      false,
      false,
      false,
      false,
      false,
      false,
      false,
      false
    ],
    [
      false,
      false,
      false,
      false,
      false,
      false,
      false,
      false,
      false,
      false,
      false,
      false,
      false
    ],
    [
      false,
      false,
      false,
      false,
      false,
      false,
      false,
      false,
      false,
      false,
      false,
      false,
      false
    ],
    [
      false,
      false,
      false,
      false,
      false,
      false,
      false,
      false,
      false,
      false,
      false,
      false,
      false
    ]
  ],
  "rarity": "Rare",
  "shipClass": "Kagerou",
  "ID": "317",
  "faction": "Sakura Empire",
  "classification": "Destroyer (DD)",
  "retrofit": false,
  "artist": "AO凹凹凹",
  "pixiv": "https://www.pixiv.net/member_illust.php?id=1248744",
  "link": "https://www.weibo.com/ultramnnice",
  "voiceActor": "https://azurlane.koumakan.jp/w/images/b/b2/Isokaze_TitleScreen.ogg",
  "armor": "Light",
  "statsHashMap": {
    "Level 120": [
      2083,
      201,
      18,
      65,
      502,
      191,
      42,
      149,
      0,
      8,
      183,
      198,
      0,
      0
    ],
    "Level 100": [
      1736,
      175,
      18,
      57,
      456,
      185,
      42,
      130,
      0,
      8,
      174,
      178,
      0,
      0
    ],
    "Base Stats": [
      336,
      74,
      18,
      12,
      97,
      71,
      42,
      28,
      0,
      2,
      67,
      49,
      0,
      0
    ]
  },
  "slot1Equipment": "DD Guns",
  "slot1Efficiency": "70% → 75%",
  "slot2Equipment": "Torpedoes",
  "slot2Efficiency": "130% → 150%",
  "slot3Equipment": "Anti-Air Guns",
  "slot3Efficiency": "70% → 75%",
  "collectionStatBonus": "Destroyer (DD) Health  +1",
  "collectionTechPoints": 5,
  "maxLimitBreakTechPoints": 10,
  "level120StatBonus": "Destroyer (DD) Accuracy  +1",
  "level120TechPoints": 8,
  "enhancementValue": [
    4,
    32,
    0,
    14
  ],
  "retireValue": [
    0,
    4,
    3,
    1
  ],
  "limitBreak1": "Gains Full Barrage I / Torpedo Efficiency +5%",
  "limitBreak2": "Max Torpedo Capacity +1 / Pre-Loaded Torpedo +1 / Torpedo Efficiency +10%",
  "limitBreak3": "Upgrades Full Barrage I→II / All Weapon Efficiency +5%",
  "skill1Name": "Accompanying Wind; CN: 伴随之风 JP: 相伴の風",
  "skill1Description": "If in same fleet with , increase own Firepower, Torpedo stat, Reload, and Anti-Air by 4% (10%).",
  "skill2Name": "All Out Assault; CN: 全弹发射 JP: 全弾発射-陽炎型",
  "skill2Description": "Every 15 (10) times the main battery is fired, trigger Full Barrage - Kagerou Class I (II)",
  "skill3Name": "",
  "skill3Description": "",
  "skins": [
    {
      "ENClientName": "Default",
      "obtainedFrom": "Default",
      "l2dModel": false,
      "spriteUrl": "https://azurlane.koumakan.jp/w/images/thumb/4/48/Isokaze.png",
      "chibiUrl": "https://azurlane.koumakan.jp/w/images/1/14/IsokazeChibi.png",
      "shipDescription": [
        "阳炎级驱逐舰十二番舰—矶风",
        "陽炎型駆逐艦十二番艦・磯風",
        "Kagerou-class destroyer number twelve – Isokaze."
      ],
      "selfIntroduction": [
        "我是十七驱的矶风，一直和滨风还有浦风、谷风在一起，啊，后来还有雪风！要说战历不会输给任何人，所以任务交给我就对啦！",
        "十七駆の磯風だ！むかしはえっと、浜風、浦風さま、谷風…あっ、雪風とも一緒にいた！カンレキなら誰にも負けないよ！だから任務は磯風に任せればよいのだ！",
        "I am Isokaze of DD17! In the past, you see, I've worked with Hamakaze, Urakaze, Tanikaze... oh, and Yukikaze! My service record stands second to none! And that's why you should put me in charge of your missions!"
      ],
      "acquisition": [
        "全军突击！……咦，这里是哪儿？！啊，我知道你，你就是浦风说的大……大将！我是矶风，将来会威震天下的大将军！",
        "全軍突撃ィ！……ととと、こ、ここはどこぉ！？あ！オマエのことは知ってる！えっと、浦風さまが言ってたた…大将！ふん！わたしは磯風、将来天下を震え上がらせる大将になるぞ！",
        "All units, attaaack! ...Wait a second, where am I?! Oh, I know you! Urakaze-sama said you're... the general! Hmph! I'm Isokaze, the one destined to become a general that will make the whole world tremble in fear!"
      ],
      "login": [
        "大将，是出击的时间啦！",
        "大将！出陣の時間だぞ！",
        "General! It's time to charge into battle!"
      ],
      "details": [
        "天！下！布！武！",
        "テンカフブ！",
        "One banner, one nation!"
      ],
      "secretaryIdle1": [
        "大将大将，来陪我玩战国游戏嘛，大将来扮演……扮演家康好了！我就是石田三成啦！",
        "大将！磯風とセンゴクごっこやってぇー！大将は……イエヤス！磯風はミツナリ！",
        "General! Come play warring states with me! You can be... Ieyasu! I'll be Mitsunari!"
      ],
      "secretaryIdle2": [
        "滨风，谷风，出发，我等的目标是——上洛！",
        "浜風！谷風！出発よ！目標は――ジョウラクだぁ！",
        "Hamakaze! Tanikaze! Let's depart! We're heading for the capital!"
      ],
      "secretaryIdle3": [
        "浦风浦风，我衣服又有点破了，能帮我修补一下嘛？",
        "浦風さま、磯風の羽織がまた破けちゃった…直して～",
        "Urakaze-sama, my coat has been torn again... Fix it for me!"
      ],
      "secretaryTouch": [
        "大将，背我起来，我要冲锋！",
        "大将、磯風をオンブして～今から敵陣に突っ込むぞー！",
        "General, give me a piggyback ride! We must charge into the enemy stronghold!"
      ],
      "secretarySpecialTouch": [
        "呀哈哈，好痒啊~",
        "ははは、くすぐったいよぉ～",
        "Hahaha, that tickles~!"
      ],
      "task": [
        "大将，任务就交给我吧！我超能干的！",
        "大将！任務は磯風に任せていいのだ！任務などガイシュウイッショクだぞ！",
        "General! Put me in charge of the mission! I'll finish it you before you can say \"set sail\"!"
      ],
      "taskComplete": [
        "大将，任务奖励发啦，有多少石呀？",
        "大将、任務報酬が来たね！何万石あるー？",
        "General, our mission rewards are here! How much koku did we receive?"
      ],
      "mail": [
        "大将，我把信件拿过来啦~",
        "大将、お手紙を持ってきたぞ！",
        "General, I have a letter for you!"
      ],
      "returnFromMission": [
        "大将，辛苦啦！听我说，听我说，刚才呢……",
        "大将、ご苦労様！えっと、えっとね！磯風から報告申し上げるぅ！あの…",
        "You make me proud, General! Hey, uh, listen! I have a report for you! You see..."
      ],
      "commission": [
        "目标港口，任务是接完成委托的姐妹们，大将号，出发！",
        "目標・母港のハトバ！委託から戻ってきたみんなを迎えるぞ！大将丸、走れ―！",
        "Our target: the base's docks! We must welcome back the commission team! Giddy-up, General!"
      ],
      "strengthening": [
        "我正是十七驱的大将军，矶风！",
        "わたしこそ十七駆の一番槍、磯風であーる！",
        "I am Isokaze, the leader of Destroyer Division 17!"
      ],
      "startingMission": [
        "一番枪是我的……哇啊啊等等我！",
        "一番槍はこの磯風が……うわああ！待ってぇ～",
        "I will lead the charge into batt... Hey, stop! Wait for me!"
      ],
      "mvp": [
        "浦风，看到我的大胜了吗！",
        "浦風さま、磯風の活躍見てくれたかー！",
        "Urakaze-sama, can you see my glorious victory?!"
      ],
      "defeat": [
        "滨风，滨风在哪儿，快来救我呜呜呜……",
        "浜風、浜風はどこぉ…磯風を助けて～",
        "Hamakaze, Hamakaze where are you... You have to save me!"
      ],
      "skillActivation": [
        "风林火山！",
        "ふ、フウリンカザン！",
        "N-nothing can stop me!"
      ],
      "lowHP": [
        "现在正是奋起的时刻！",
        "踏ん張る時よ！",
        "I will never back down!"
      ],
      "affinityDisappointed": [
        "走开，我不要跟尼玩了，滨风，滨风尼在哪儿？",
        "ふん！もう大将とは遊ばないよ！浜風～浜風はどこぉー？",
        "Hmph! I'm done playing with you! Hamakaze, Tanikaze, where are you?"
      ],
      "affinityStranger": [
        "我的知识都是浦风教的，浦风懂很多东西呢！不过我最好的朋友还是滨风，嘿嘿~",
        "センゴクのこと？全部浦風さまが教えてくれた！浦風さまは物知りだぞ！でも磯風の一番の親友はやっぱり浜風なの！えへへ～",
        "How I know so much? Urakaze-sama taught me everything about the warring states! She's really smart! But Hamakaze is still my best friend in the end! Heheheh~"
      ],
      "affinityFriendly": [
        "西军突击！拿下东军！让我看看，接下来是……哇呀呀，小早川秀秋被策反啦！大将尼好坏，我要，我要，呜呜呜呜……",
        "西軍突撃！東軍を討つぞー！えっと次は……あわわ！ヒデアキが引き抜かれた！大将ずるいよ！磯風は…うぅぅ……",
        "Western Army, attack! Fire on the Eastern Army! Our next move will be... Oh no! Hideaki was lured away! That's unfair, General! Darn, now I'm... *Sob*..."
      ],
      "affinityLike": [
        "大将，有空陪我玩游戏嘛？没有嘛？真的没有嘛？我来帮尼工作也没有嘛？我给尼捶背也没有嘛？……耶！我最喜欢大将啦！",
        "大将、磯風とゲームしようよ～え！忙しいからできないの！本当に？お仕事を手伝うよ？お肩を叩いてあげるよ？……やったぁ！大将大好き！",
        "General, let's play a game! Huh?! You've got work to do?! You really do? Do you want me to help? Then how about a massage? ...Hooray! I love you, General!"
      ],
      "affinityLove": [
        "大将大将，浦风说我现在都只跟大将玩滨风要生气啦！但我就是想和大将玩嘛……所以呢，所以呢，我们一起去找滨风玩吧！",
        "大将、わたし最近浜風に冷たいって浦風さまに怒られそうになったの！でも磯風やっぱり大将と遊びたいの……だから大将、一緒に浜風と遊びに行こう！",
        "General, Urakaze-sama seemed angry at me and said I've started being cold to Hamakaze! But I still want to play with you... So come on! Let's go play together with Hamakaze!"
      ],
      "pledge": [
        "大将，以后要是有人欺负尼，告诉我，我一定带着滨风来帮尼报仇，因为我和大将还有滨风是最好的朋友~",
        "大将、今度いじめられたら磯風に教えて？磯風は浜風を連れて仇を取ってやるぞ。大将と磯風と浜風はお友達してるんだから！",
        "General, if anyone starts being mean to you then tell me. Hamakaze and I will go and get revenge on them for you. We're here for you, because we're all friends!"
      ],
      "additionalVoiceLine1": [
        "(Sortie with Hamakaze) 滨风，随我冲锋！",
        "(Sortie with Hamakaze) 浜風、わたしに続けぃ！",
        "(Sortie with Hamakaze) Hamakaze, follow my lead!"
      ],
      "giftDescriptionValentines2019": [
        "大将大将，浦风说这是给最喜欢的人送传家宝的节日，矶风没有传家宝，就把这个甜甜的糖果给你吧！",
        "大将！浦風さまが今日こそ一番気に入った相手に家宝を下賜する日だって！磯風は家宝を持っていないから、この甘いお菓子をあげる！",
        null
      ],
      "giftDescriptionValentines2020": [
        null,
        null,
        "General! Urakaze bestowed upon me this chocolate as a commendation! But I think it would be a little weird to make it an heirloom, so I decided to share it with you, General!"
      ],
      "selfIntroductionUrl": [
        "https://azurlane.koumakan.jp/w/images/1/17/Isokaze_SelfIntroJP.ogg",
        "https://azurlane.koumakan.jp/w/images/1/17/Isokaze_SelfIntroJP.ogg",
        "https://azurlane.koumakan.jp/w/images/1/17/Isokaze_SelfIntroJP.ogg"
      ],
      "acquisitionUrl": [
        "https://azurlane.koumakan.jp/w/images/c/c9/Isokaze_IntroJP.ogg",
        "https://azurlane.koumakan.jp/w/images/c/c9/Isokaze_IntroJP.ogg",
        "https://azurlane.koumakan.jp/w/images/c/c9/Isokaze_IntroJP.ogg"
      ],
      "loginUrl": [
        "https://azurlane.koumakan.jp/w/images/a/ac/Isokaze_LogJP.ogg",
        "https://azurlane.koumakan.jp/w/images/a/ac/Isokaze_LogJP.ogg",
        "https://azurlane.koumakan.jp/w/images/a/ac/Isokaze_LogJP.ogg"
      ],
      "detailsUrl": [
        "https://azurlane.koumakan.jp/w/images/5/58/Isokaze_DetailsJP.ogg",
        "https://azurlane.koumakan.jp/w/images/5/58/Isokaze_DetailsJP.ogg",
        "https://azurlane.koumakan.jp/w/images/5/58/Isokaze_DetailsJP.ogg"
      ],
      "secretaryIdle1Url": [
        "https://azurlane.koumakan.jp/w/images/8/8b/Isokaze_SecIdle1JP.ogg",
        "https://azurlane.koumakan.jp/w/images/8/8b/Isokaze_SecIdle1JP.ogg",
        "https://azurlane.koumakan.jp/w/images/8/8b/Isokaze_SecIdle1JP.ogg"
      ],
      "secretaryIdle2Url": [
        "https://azurlane.koumakan.jp/w/images/d/d5/Isokaze_SecIdle2JP.ogg",
        "https://azurlane.koumakan.jp/w/images/d/d5/Isokaze_SecIdle2JP.ogg",
        "https://azurlane.koumakan.jp/w/images/d/d5/Isokaze_SecIdle2JP.ogg"
      ],
      "secretaryIdle3Url": [
        "https://azurlane.koumakan.jp/w/images/9/96/Isokaze_SecIdle3JP.ogg",
        "https://azurlane.koumakan.jp/w/images/9/96/Isokaze_SecIdle3JP.ogg",
        "https://azurlane.koumakan.jp/w/images/9/96/Isokaze_SecIdle3JP.ogg"
      ],
      "secretaryTouchUrl": [
        "https://azurlane.koumakan.jp/w/images/9/9a/Isokaze_Sec1JP.ogg",
        "https://azurlane.koumakan.jp/w/images/9/9a/Isokaze_Sec1JP.ogg",
        "https://azurlane.koumakan.jp/w/images/9/9a/Isokaze_Sec1JP.ogg"
      ],
      "secretarySpecialTouchUrl": [
        "https://azurlane.koumakan.jp/w/images/a/a6/Isokaze_Sec2JP.ogg",
        "https://azurlane.koumakan.jp/w/images/a/a6/Isokaze_Sec2JP.ogg",
        "https://azurlane.koumakan.jp/w/images/a/a6/Isokaze_Sec2JP.ogg"
      ],
      "taskUrl": [
        "https://azurlane.koumakan.jp/w/images/e/ea/Isokaze_TaskJP.ogg",
        "https://azurlane.koumakan.jp/w/images/e/ea/Isokaze_TaskJP.ogg",
        "https://azurlane.koumakan.jp/w/images/e/ea/Isokaze_TaskJP.ogg"
      ],
      "taskCompleteUrl": [
        "https://azurlane.koumakan.jp/w/images/9/9c/Isokaze_TaskCJP.ogg",
        "https://azurlane.koumakan.jp/w/images/9/9c/Isokaze_TaskCJP.ogg",
        "https://azurlane.koumakan.jp/w/images/9/9c/Isokaze_TaskCJP.ogg"
      ],
      "mailUrl": [
        "https://azurlane.koumakan.jp/w/images/d/d5/Isokaze_MailJP.ogg",
        "https://azurlane.koumakan.jp/w/images/d/d5/Isokaze_MailJP.ogg",
        "https://azurlane.koumakan.jp/w/images/d/d5/Isokaze_MailJP.ogg"
      ],
      "returnFromMissionUrl": [
        "https://azurlane.koumakan.jp/w/images/8/80/Isokaze_MissionFinJP.ogg",
        "https://azurlane.koumakan.jp/w/images/8/80/Isokaze_MissionFinJP.ogg",
        "https://azurlane.koumakan.jp/w/images/8/80/Isokaze_MissionFinJP.ogg"
      ],
      "commissionUrl": [
        "https://azurlane.koumakan.jp/w/images/6/6a/Isokaze_CommissionJP.ogg",
        "https://azurlane.koumakan.jp/w/images/6/6a/Isokaze_CommissionJP.ogg",
        "https://azurlane.koumakan.jp/w/images/6/6a/Isokaze_CommissionJP.ogg"
      ],
      "strengtheningUrl": [
        "https://azurlane.koumakan.jp/w/images/0/0b/Isokaze_StrJP.ogg",
        "https://azurlane.koumakan.jp/w/images/0/0b/Isokaze_StrJP.ogg",
        "https://azurlane.koumakan.jp/w/images/0/0b/Isokaze_StrJP.ogg"
      ],
      "startingMissionUrl": [
        "https://azurlane.koumakan.jp/w/images/c/cd/Isokaze_MissionStartJP.ogg",
        "https://azurlane.koumakan.jp/w/images/c/cd/Isokaze_MissionStartJP.ogg",
        "https://azurlane.koumakan.jp/w/images/c/cd/Isokaze_MissionStartJP.ogg"
      ],
      "mvpUrl": [
        "https://azurlane.koumakan.jp/w/images/b/b1/Isokaze_MVPJP.ogg",
        "https://azurlane.koumakan.jp/w/images/b/b1/Isokaze_MVPJP.ogg",
        "https://azurlane.koumakan.jp/w/images/b/b1/Isokaze_MVPJP.ogg"
      ],
      "defeatUrl": [
        "https://azurlane.koumakan.jp/w/images/9/97/Isokaze_DefeatJP.ogg",
        "https://azurlane.koumakan.jp/w/images/9/97/Isokaze_DefeatJP.ogg",
        "https://azurlane.koumakan.jp/w/images/9/97/Isokaze_DefeatJP.ogg"
      ],
      "skillActivationUrl": [
        "https://azurlane.koumakan.jp/w/images/a/ad/Isokaze_SkillActivationJP.ogg",
        "https://azurlane.koumakan.jp/w/images/a/ad/Isokaze_SkillActivationJP.ogg",
        "https://azurlane.koumakan.jp/w/images/a/ad/Isokaze_SkillActivationJP.ogg"
      ],
      "lowHPUrl": [
        "https://azurlane.koumakan.jp/w/images/6/63/Isokaze_LowHPJP.ogg",
        "https://azurlane.koumakan.jp/w/images/6/63/Isokaze_LowHPJP.ogg",
        "https://azurlane.koumakan.jp/w/images/6/63/Isokaze_LowHPJP.ogg"
      ],
      "affinityDisappointedUrl": [
        "https://azurlane.koumakan.jp/w/images/5/5e/Isokaze_Affinity0JP.ogg",
        "https://azurlane.koumakan.jp/w/images/5/5e/Isokaze_Affinity0JP.ogg",
        "https://azurlane.koumakan.jp/w/images/5/5e/Isokaze_Affinity0JP.ogg"
      ],
      "affinityStrangerUrl": [
        "https://azurlane.koumakan.jp/w/images/a/ad/Isokaze_Affinity1JP.ogg",
        "https://azurlane.koumakan.jp/w/images/a/ad/Isokaze_Affinity1JP.ogg",
        "https://azurlane.koumakan.jp/w/images/a/ad/Isokaze_Affinity1JP.ogg"
      ],
      "affinityFriendlyUrl": [
        "https://azurlane.koumakan.jp/w/images/c/ce/Isokaze_Affinity2JP.ogg",
        "https://azurlane.koumakan.jp/w/images/c/ce/Isokaze_Affinity2JP.ogg",
        "https://azurlane.koumakan.jp/w/images/c/ce/Isokaze_Affinity2JP.ogg"
      ],
      "affinityLikeUrl": [
        "https://azurlane.koumakan.jp/w/images/6/63/Isokaze_Affinity3JP.ogg",
        "https://azurlane.koumakan.jp/w/images/6/63/Isokaze_Affinity3JP.ogg",
        "https://azurlane.koumakan.jp/w/images/6/63/Isokaze_Affinity3JP.ogg"
      ],
      "affinityLoveUrl": [
        "https://azurlane.koumakan.jp/w/images/c/cc/Isokaze_Affinity4JP.ogg",
        "https://azurlane.koumakan.jp/w/images/c/cc/Isokaze_Affinity4JP.ogg",
        "https://azurlane.koumakan.jp/w/images/c/cc/Isokaze_Affinity4JP.ogg"
      ],
      "pledgeUrl": [
        "https://azurlane.koumakan.jp/w/images/2/2f/Isokaze_PledgeJP.ogg",
        "https://azurlane.koumakan.jp/w/images/2/2f/Isokaze_PledgeJP.ogg",
        "https://azurlane.koumakan.jp/w/images/2/2f/Isokaze_PledgeJP.ogg"
      ],
      "additionalVoiceLine1Url": [
        "https://azurlane.koumakan.jp/w/images/2/26/Isokaze_Extra1JP.ogg",
        "https://azurlane.koumakan.jp/w/images/2/26/Isokaze_Extra1JP.ogg",
        "https://azurlane.koumakan.jp/w/images/2/26/Isokaze_Extra1JP.ogg"
      ]
    },
    {
      "ENClientName": "New Year's Campaign",
      "ENClientAvailability": "Limited",
      "CNClientName": "新年合战",
      "CNClientAvailability": "Limited",
      "JPClientName": "新年大合戦",
      "JPClientAvailability": "Limited",
      "obtainedFrom": "Skin Shop",
      "cost": "Gem 780",
      "l2dModel": false,
      "spriteUrl": "https://azurlane.koumakan.jp/w/images/thumb/2/2f/IsokazeNew_Year.png",
      "chibiUrl": "https://azurlane.koumakan.jp/w/images/c/c6/IsokazeNew_YearChibi.png",
      "shipDescription": [
        "大将大将，看，新年的衣服！浦风做的！新的一年也要陪我玩战国游戏哦！",
        "大将大将！見て見て！お正月の服！浦風さまが作ってくれた！今年も一緒にセンゴクごっこをよろしく！",
        "General, General, look! It's my New Year's outfit! Urakaze made it for me! Let's play a bunch of Sengoku wargames this year as well!"
      ],
      "acquisition": [
        "大将大将，看，新年的衣服！浦风做的！新的一年也要陪我玩战国游戏哦！",
        "大将大将！見て見て！お正月の服！浦風さまが作ってくれた！今年も一緒にセンゴクごっこをよろしく！",
        "General, General, look! It's my New Year's outfit! Urakaze made it for me! Let's play a bunch of Sengoku wargames this year as well!"
      ],
      "login": [
        "大将，新年快乐！",
        "大将！あけましておめでとう！",
        "General, Happy New Year!"
      ],
      "details": [
        "大将大将，我要压岁钱！",
        "大将！お年玉がほしい！",
        "General, I want my red envelope!"
      ],
      "secretaryIdle1": [
        "哇，下雪啦！大将，我们叫上大家，来雪合战吧！",
        "わあ！雪だ！大将、みんなを呼んできて雪合戦しようよ！",
        "Woah! It's snowing! General, let's call everyone out and have a snowball fight!"
      ],
      "secretaryIdle2": [
        "为什么大家到了冬天都无精打采的，我觉得雪超好玩的欸？",
        "なんでみんな冬になると元気がなくなるのかな……冬は雪が降るとすごく楽しいのに？",
        "Why is everyone so sluggish during the winter? I think playing in the snow is suuuuper fun!"
      ],
      "secretaryIdle3": [
        "大将，尼看尼看，老虎，嘎哦！呀哈哈~~",
        "大将大将！見て！トラさんだ！がお！あははは～",
        "General, General, look! It's a tiger! Rooooaarrr! Ahahaha~"
      ],
      "secretaryTouch": [
        "欸？大将，我不冷哦~呀哈哈，不要摸我肚子嘛，好痒",
        "ふえ？大将？磯風は別に寒くないよ？……あはははお腹さわるのやめて～ぐすぐったいよぉ～",
        "Huh? General, I'm not cold~ Ahaha, stop rubbing my belly, it tickles!"
      ],
      "taskComplete": [
        "大将，这些是什么，难道是新年礼物嘛？",
        "大将、これはなぁに？新年の贈り物？",
        "General, what are these? New Year's presents?"
      ],
      "affinityLove": [
        "大将大将，新年参拜的话，一定要叫我哦？就算我睡懒觉也要叫我哦？今年我一定要和大将一起去！",
        "大将大将！初詣はわたしを絶対に連れて行って！…わたしが寝坊しても絶対に起こしてね！今年こそ大将と一緒に行きたぁい！",
        "General, General! Make sure to wake me up for the New Year's shrine visit! Even if I sleep in, make sure to come get me! This year, we definitely need to go together!"
      ]
    }
  ],
  "retrofitNodes": []
}